nmm-0.0.14.dist-info/LICENSE.md
nmm-0.0.14.dist-info/RECORD
nmm-0.0.14.dist-info/WHEEL
nmm-0.0.14.dist-info/top_level.txt
nmm-0.0.14.dist-info/METADATA
nmm/_output.py
nmm/nmm.h
nmm/_cdata.py
nmm/__init__.py
nmm/_codon_prob.py
nmm/_state.py
nmm/_table.py
nmm/_ffi.abi3.so
nmm/_translator.py
nmm/_input.py
nmm/_testit.py
nmm/_alphabet.py
nmm/_codon.py
nmm/wrap.py
nmm/_model.py
nmm/test/test_sequence.py
nmm/test/test_codon_prob.py
nmm/test/test_codon.py
nmm/test/test_table.py
nmm/test/__init__.py
nmm/test/test_io.py
nmm/test/test_state.py
nmm/test/test_alphabet.py
nmm/test/test_hmm.py
nmm/test/test_fragment.py
nmm/.dylibs/libimm.0.0.9.dylib
nmm/.dylibs/libnmm.0.0.7.dylib
