Metadata-Version: 2.1
Name: nmm
Version: 0.0.14
Summary: Hidden Markov models for nucleotide sequences
Home-page: https://github.com/EBI-Metagenomics/nmm-py
Author: Danilo Horta
Author-email: horta@ebi.ac.uk
Maintainer: Danilo Horta
Maintainer-email: horta@ebi.ac.uk
License: MIT
Download-URL: https://github.com/EBI-Metagenomics/nmm-py
Keywords: hmm,profile,dna,protein
Platform: Windows
Platform: MacOS
Platform: Linux
Classifier: Development Status :: 5 - Production/Stable
Classifier: License :: OSI Approved :: MIT License
Classifier: Operating System :: OS Independent
Classifier: Programming Language :: Python
Requires-Dist: cffi (>=1.13.1)
Requires-Dist: imm (>=0.0.2)
Requires-Dist: pytest (>=5.2.1)
